{"_id":"56260be69034736a68296585","createDate":"2015-10-20T09:39:50.134Z","createUserId":"55e5c6995a761f8a46b34399","editDate":"2017-06-09T09:47:25.848Z","editUserId":"55e5c6995a761f8a46b34399","title":"Cancer","content":"<p>Cancer is a generic term for a large group of diseases that can affect any part of the body. Other terms used are malignant tumours and neoplasms. One defining feature of cancer is the rapid creation of abnormal cells that grow beyond their usual boundaries, and which can then invade adjoining parts of the body and spread to other organs, the latter process is referred to as metastasizing. Metastases are a major cause of death from cancer.<br></p>","parentId":"578227126d366f0f3cb8e350","groupId":100,"childrenCount":{"topics":{"total":3,"accepted":3,"pending":0,"rejected":0},"arguments":{"total":6,"accepted":6,"pending":0,"rejected":0},"questions":{"total":3,"accepted":3,"pending":0,"rejected":0},"issues":{"total":0,"accepted":0,"pending":0,"rejected":0,"acceptedCritical":0},"opinions":{"total":0,"accepted":0,"pending":0,"rejected":0}},"outline":[],"ethicalStatus":{"hasValue":false},"private":false,"screeningStatus":0,"tags":[],"ownerType":-1,"ownerId":null,"references":"<p><a href=\"http://www.who.int/mediacentre/factsheets/fs297/en/\">http://www.who.int/mediacentre/factsheets/fs297/en/</a></p>","screening":{"history":[],"status":1},"contentPreview":"Cancer is a generic term for a large group of diseases that can affect any part of the body. Other terms used are malignant tumours and neoplasms. One defining feature of cancer is the rapid creation of abnormal cells that grow beyond their usual boundaries,...","contextTitle":"","friendlyUrl":"cancer","referenceDate":null,"icon":""}