{"_id":"57c123f9fd5c737a358f5678","parentId":"56260de29034736a68296586","groupId":100,"createDate":"2016-08-27T05:24:09.428Z","createUserId":"55e5c6995a761f8a46b34399","editDate":"2016-10-07T11:14:39.870Z","editUserId":"55e5c6995a761f8a46b34399","references":"","title":"Key claims of evolution","content":"","icon":"","outline":[],"ethicalStatus":{"hasValue":false},"ownerType":-1,"ownerId":null,"childrenCount":{"questions":0,"issues":0,"opinions":0,"topics":0,"arguments":0},"contextTitle":"","tags":[]}