{"_id":"57c5aa16c494751418003aad","parentId":"578227126d366f0f3cb8e350","groupId":100,"createDate":"2016-08-30T15:45:26.076Z","createUserId":"55e5c6995a761f8a46b34399","editDate":"2016-08-30T16:36:21.588Z","editUserId":"55e5c6995a761f8a46b34399","references":"<p><a href=\"http://edition.cnn.com/2016/08/30/health/zika-around-the-world/index.html\">http://edition.cnn.com/2016/08/30/health/zika-around-the-world/index.html</a><a href=\"http://edition.cnn.com/2016/08/30/health/zika-around-the-world/index.html\"></a><br><a href=\"https://www.cdc.gov/zika/about/index.html\">https://www.cdc.gov/zika/about/index.html</a><br></p>","title":"Zika Virus","content":"","outline":[],"ownerType":-1,"ownerId":null}