{"_id":"57d6c9d117ff5bbd6def4875","parentId":"57aa74e0b663fb1072c7766d","createDate":"2016-09-12T15:29:21.625Z","createUserId":"55e5c6995a761f8a46b34399","ethicalStatus":{"hasValue":false},"icon":"","editDate":"2016-09-12T15:29:21.625Z","editUserId":"55e5c6995a761f8a46b34399","references":"","contextTitle":"Organizations","title":"Organizations in the Philippines","content":"","childrenCount":{"topics":{"accepted":12,"pending":0,"rejected":0,"total":12},"arguments":{"accepted":0,"pending":0,"rejected":0,"total":0},"questions":{"accepted":0,"pending":0,"rejected":0,"total":0},"issues":{"accepted":0,"pending":0,"rejected":0,"total":0},"opinions":{"accepted":0,"pending":0,"rejected":0,"total":0}},"outline":[],"private":false,"screeningStatus":0,"tags":[],"ownerType":-1,"ownerId":null,"screening":{"status":1,"history":[]}}