{"_id":"58f653e97ef128cd54260dbf","screening":{"history":[],"status":1},"createDate":"2017-04-18T17:59:05.626Z","createUserId":"55e5c6995a761f8a46b34399","parentId":"57e35898e667695b74f82966","ethicalStatus":{"hasValue":false},"icon":null,"tags":[],"referenceDate":null,"editDate":"2017-04-18T18:13:02.961Z","editUserId":"55e5c6995a761f8a46b34399","friendlyUrl":"issue-and-opinion-structure","references":"","contextTitle":"","title":"Issue and Opinion Structure","contentPreview":"Possible Hierarchies\n\n 1. Opinion > Opinion (child)\n 2. ... Opinion > Issue > Opinion > Opinion (child)\n 3. Issue > Opinion > Opinion (child)\n 4. Issue > Opinion > Issue","content":"<p>Possible Hierarchies</p><ol><li>Opinion &gt; Opinion (child)</li><li>... Opinion &gt; Issue &gt; Opinion &gt; Opinion (child)</li><li>Issue &gt; Opinion &gt; Opinion (child)</li><li><strike>Issue &gt; Opinion &gt; Issue</strike></li></ol>","__v":0,"ownerId":null,"ownerType":-1,"private":false,"outline":[],"childrenCount":{"opinions":{"rejected":0,"pending":0,"accepted":0,"total":0},"issues":{"acceptedCritical":0,"rejected":0,"pending":0,"accepted":0,"total":0},"questions":{"rejected":0,"pending":0,"accepted":0,"total":0},"arguments":{"rejected":0,"pending":0,"accepted":2,"total":2},"topics":{"rejected":0,"pending":0,"accepted":0,"total":0}}}