{"_id":"57ff43c29a2079dd156f7d67","createDate":"2016-10-13T08:20:18.158Z","createUserId":"55e5c6995a761f8a46b34399","ownerType":1,"ownerId":"57ed490e6c746e1210b0f31e","against":false,"threadId":null,"parentId":null,"ethicalStatus":{"hasValue":false},"typeId":1,"editDate":"2016-10-13T08:21:42.192Z","editUserId":"55e5c6995a761f8a46b34399","references":"<p><a href=\"https://www.scientificamerican.com/article/an-epidemic-of-false-claims/\">https://www.scientificamerican.com/article/an-epidemic-of-false-claims/</a><br><a href=\"https://repository.library.georgetown.edu/handle/10822/1017114\">https://repository.library.georgetown.edu/handle/10822/1017114</a><br><a href=\"https://www.ncbi.nlm.nih.gov/pubmed/21608392\">https://www.ncbi.nlm.nih.gov/pubmed/21608392</a><br></p>","title":"There is an epidemic of false claims","content":"<p>False positives and exaggerated results in peer-reviewed scientific studies have reached epidemic proportions in recent years. The problem is rampant in economics, the social sciences and even the natural sciences, but it is particularly egregious in biomedicine. Many studies that claim some drug or treatment is beneficial have turned out not to be true. We need only look to conflicting findings about beta-carotene, vitamin E, hormone treatments, Vioxx and Avandia. Even when effects are genuine, their true magnitude is often smaller than originally claimed.</p>","tags":[],"private":false,"screeningStatus":0}