{"_id":"5a5f7be2998bd57baeec6ba9","__v":0,"childrenCount":{"arguments":{"total":0,"accepted":0,"pending":0,"rejected":0},"questions":{"total":0,"accepted":0,"pending":0,"rejected":0},"issues":{"total":0,"accepted":0,"pending":0,"rejected":0,"acceptedCritical":0},"opinions":{"total":0,"accepted":0,"pending":0,"rejected":0}},"content":"In 2009, the Omidyar Network donated $2 million over two years to the Wikimedia Foundation, and at the same time, Matt Halpin of Omidyar Network was appointed to Wikimedia's board of directors.","contentPreview":"In 2009, the Omidyar Network donated $2 million over two years to the Wikimedia Foundation, and at the same time, Matt Halpin of Omidyar Network was appointed to Wikimedia's board of directors.","title":"Omidyar Network donated $2 million to the Wikimedia Foundation","references":"<p><a href=\"https://wikimediafoundation.org/wiki/Press_releases/Omidyar_Network_Grant_August_2009\">https://wikimediafoundation.org/wiki/Press_releases/Omidyar_Network_Grant_August_2009</a><a href=\"https://wikimediafoundation.org/wiki/Press_releases/Omidyar_Network_Grant_August_2009\"></a></p><p><a href=\"https://en.wikipedia.org/wiki/Omidyar_Network?wprov=sfti1\">https://en.wikipedia.org/wiki/Omidyar_Network</a><br><br></p>","friendlyUrl":"omidyar-network-donated-2-million-to-the-wikimedia-foundation","referenceDate":null,"editUserId":"55e5c6995a761f8a46b34399","editDate":"2018-01-17T16:37:54.689Z","typeId":1,"against":false,"tags":[],"ethicalStatus":{"hasValue":false},"private":false,"parentId":null,"threadId":null,"ownerId":"5a5f7b2b998bd57baeec6ba8","ownerType":1,"createUserId":"55e5c6995a761f8a46b34399","createDate":"2018-01-17T16:37:54.689Z","screening":{"history":[],"status":1},"categoryId":"563aca50b49485b50bb45070"}